sized_ints/__init__.py
sized_ints-0.1.6.dist-info/LICENSE
sized_ints-0.1.6.dist-info/METADATA
sized_ints-0.1.6.dist-info/WHEEL
sized_ints-0.1.6.dist-info/top_level.txt
sized_ints-0.1.6.dist-info/RECORD
