Metadata-Version: 2.1
Name: sized-ints
Version: 0.1.6
Summary: convenient add sized ints to python (u8, i8, int64_t, etc)
Home-page: https://github.com/TG-Techie/python-sized-ints
Author: TG-Techie (Jonah Y-M)
Author-email: tgtechie01@gmail.com
License: UNKNOWN
Platform: UNKNOWN
Classifier: Programming Language :: Python :: 3
Classifier: License :: OSI Approved :: MIT License
Classifier: Operating System :: OS Independent
Requires-Python: >=3.6
